[
  {
    "id": "1",
    "imgURL": "https://i.ibb.co/Rcv4T8F/ki-T9-JYt-Vr58.jpg",
    "tag": "free"
  },
  {
    "id": "2",
    "imgURL": "https://i.ibb.co/3NZc254/dm-Gm-Epf-NYPI.jpg",
    "tag": "new"
  },
  {
    "id": "3",
    "imgURL": "https://i.ibb.co/r0rR5nr/AO3-Yd-Np-Vd-W4.jpg",
    "tag": "pro"
  },
  {
    "id": "4",
    "imgURL": "https://i.ibb.co/cXBrtdZ/YOj-KKFXa7-B4.jpg",
    "tag": "pro"
  },
  {
    "id": "5",
    "imgURL": "https://i.ibb.co/dsvzgKG/A3-Nfm56ix-Z8.jpg",
    "tag": "free"
  },
  {
    "id": "6",
    "imgURL": "https://i.ibb.co/Rcv4T8F/ki-T9-JYt-Vr58.jpg",
    "tag": "free"
  },
  {
    "id": "7",
    "imgURL": "https://i.ibb.co/nPKp1hK/yve-Fu-P6b-REo.jpg",
    "tag": "new"
  },
  {
    "id": "8",
    "imgURL": "https://i.ibb.co/WGnVnyF/WCdah-Fst3-R0.jpg",
    "tag": "new"
  },
  {
    "id": "9",
    "imgURL": "https://i.ibb.co/fk8WQDR/M2u-Hhq-Miy-Qo.jpg",
    "tag": "free"
  },
  {
    "id": "10",
    "imgURL": "https://i.ibb.co/pKyy9DY/Ri3-C2-Se-Qrw.jpg",
    "tag": "pro"
  }
]
